Metadata-Version: 2.1
Name: libtabular
Version: 0.0.3
Summary: Utility functions for reading and writing CSV files with metadata headers.
Home-page: https://github.com/rocdata/libtabular
Author: Ivan Savov
Author-email: ivan.savov@gmail.com
License: MIT
Project-URL: Documentation, https://github.com/rocdata/libtabular/tree/main/docs
Project-URL: Issue Tracker, https://github.com/rocdata/libtabular/issues
Keywords: CSV,Excel,spreadhseets,metadata
Platform: UNKNOWN
Classifier: Development Status :: 2 - Pre-Alpha
Classifier: Intended Audience :: Developers
Classifier: License :: OSI Approved :: MIT License
Classifier: Operating System :: Unix
Classifier: Operating System :: POSIX
Classifier: Operating System :: Microsoft :: Windows
Classifier: Programming Language :: Python
Classifier: Programming Language :: Python :: 3
Classifier: Programming Language :: Python :: 3.6
Classifier: Programming Language :: Python :: 3.7
Classifier: Programming Language :: Python :: 3.8
Classifier: Programming Language :: Python :: Implementation :: CPython
Classifier: Programming Language :: Python :: Implementation :: PyPy
Classifier: Topic :: Utilities
Requires-Python: >=3.6
